mkdocs_asciinema/__init__.py
mkdocs_asciinema/plugin.py
mkdocs_asciinema-0.0.1.dist-info/entry_points.txt
mkdocs_asciinema-0.0.1.dist-info/WHEEL
mkdocs_asciinema-0.0.1.dist-info/METADATA
mkdocs_asciinema-0.0.1.dist-info/license_files/LICENSE
mkdocs_asciinema-0.0.1.dist-info/RECORD
