Metadata-Version: 2.1
Name: mkdocs-asciinema
Version: 0.0.1
Summary: A Mkdocs Plugin for asciinema player
Author-email: ZhenyuanLau <zhenyuanlau@outlook.com>
Requires-Python: >=3.9
Requires-Dist: beautifulsoup4
Requires-Dist: mkdocs
